anysell/__init__.py
anysell/config.py
anysell/main.py
anysell/sellers/__init__.py
anysell/sellers/base.py
anysell/sellers/bazos.py
anysell/sellers/item.py
anysell-0.0.5.dist-info/LICENSE
anysell-0.0.5.dist-info/METADATA
anysell-0.0.5.dist-info/WHEEL
anysell-0.0.5.dist-info/entry_points.txt
anysell-0.0.5.dist-info/top_level.txt
anysell-0.0.5.dist-info/RECORD
