Metadata-Version: 2.1
Name: anysell
Version: 0.0.5
Summary: Sell any item you want on any market platform easily.
Home-page: https://github.com/maroshmka/anysell
Author: Mário Hunka
Author-email: hunka.mario@gmail.com
License: UNKNOWN
Keywords: automatization,sale,goods,cli
Platform: UNKNOWN
Classifier: Development Status :: 4 - Beta
Classifier: Intended Audience :: Developers
Classifier: License :: OSI Approved :: MIT License
Classifier: Programming Language :: Python :: 3.9
Classifier: Programming Language :: Python :: 3 :: Only
Requires-Python: >=3.6, <4
Requires-Dist: requests (==2.25.1.)
Requires-Dist: beautifulsoup4 (==4.9.3)
Requires-Dist: click (==8.0.0a1)
Requires-Dist: PyYAML (==5.4.1)
